kblackjack/__init__.py
kblackjack/__main__.py
kblackjack/card.py
kblackjack/main.py
kblackjack/players.py
kblackjack-0.1.1.dist-info/LICENSE
kblackjack-0.1.1.dist-info/METADATA
kblackjack-0.1.1.dist-info/WHEEL
kblackjack-0.1.1.dist-info/entry_points.txt
kblackjack-0.1.1.dist-info/top_level.txt
kblackjack-0.1.1.dist-info/RECORD
