Metadata-Version: 2.1
Name: kblackjack
Version: 0.1.1
Summary: A simple single-player blackjack simulator
Home-page: https://git.kasad.com/kblackjack/about
Author: Kian Kasad
Author-email: dev@kasad.com
License: BSD-2-Clause-Patent
Platform: UNKNOWN
Requires-Python: >=3.6
License-File: LICENSE
